objict/__init__.py
pyobjict-2.0.9.dist-info/LICENSE
pyobjict-2.0.9.dist-info/METADATA
pyobjict-2.0.9.dist-info/WHEEL
pyobjict-2.0.9.dist-info/RECORD
