Metadata-Version: 2.3
Name: pyobjict
Version: 2.0.9
Summary: A Python dict that supports attribute-style access as well as hierarchical keys, JSON serialization, ZIP compression, and more.
License: MIT
Keywords: dict,object,attribute,json,zip,hierarchical
Author: Ian Starnes
Author-email: ians@311labs.com
Requires-Python: >=3.8
Classifier: Development Status :: 5 - Production/Stable
Classifier: Intended Audience :: Developers
Classifier: License :: OSI Approved :: MIT License
Classifier: Programming Language :: Python :: 3
Classifier: Programming Language :: Python :: 3.8
Classifier: Programming Language :: Python :: 3.9
Classifier: Programming Language :: Python :: 3.10
Classifier: Programming Language :: Python :: 3.11
Classifier: Programming Language :: Python :: 3.12
Classifier: Topic :: Software Development :: Libraries :: Python Modules
Project-URL: Homepage, https://github.com/311labs/objict
Project-URL: Issues, https://github.com/311labs/objict/issues
Project-URL: Repository, https://github.com/311labs/objict
